transude/__init__.py
transude/data_frame_filter.py
transude/data_frame_filter_factory.py
transude/data_frame_filter_manager.py
transude-2.0.0.dist-info/LICENSE
transude-2.0.0.dist-info/METADATA
transude-2.0.0.dist-info/WHEEL
transude-2.0.0.dist-info/top_level.txt
transude-2.0.0.dist-info/RECORD
