Metadata-Version: 2.1
Name: transude
Version: 2.0.0
Summary: Simple tool set for filtering DataFrames by building queries from one or more filters.
Author: Ewvyx
Project-URL: Homepage, https://github.com/gizix/transude
Project-URL: Bug Tracker, https://github.com/gizix/transude/issues
Classifier: Programming Language :: Python :: 3
Classifier: License :: OSI Approved :: MIT License
Classifier: Operating System :: OS Independent
Requires-Python: >=3.10
License-File: LICENSE
